[
  {
    "name":"Dobly walya bolav r mazya dj la",
    "imgSrc": "songs/Marathi songs/music.png",
    "downloadLink":"songs/Marathi songs/Dobly walya bolav r mazya dj la.mp3",
  "pagename":"Dobly-walya-bolv-r"
  }, {
    "name":"Aaplich hava",
    "imgSrc": "songs/Marathi songs/music.png",
    "downloadLink":"songs/Marathi songs/Aaplich hava.mp3",
  "pagename":"Aaplich-hava"
  }   ,{
    "name":"Aatach bya ka bavrl - sairat",
    "imgSrc": "songs/Marathi songs/music.png",
    "downloadLink":"songs/Marathi songs/Aatach bya ka bavrl - sairat.mp3",
  "pagename":"Aatach-bya-ka-bavrl"
  }   ,{
    "name":"Apsra aali",
    "imgSrc": "songs/Marathi songs/music.png",
    "downloadLink":"songs/Marathi songs/Apsra aali.mp3",
  "pagename":"Apsra-aali"
  }   ,{
    "name":"Baipan bhari g",
    "imgSrc": "songs/Marathi songs/music.png",
    "downloadLink":"songs/Marathi songs/Baipan bhari g.mp3",
  "pagename":"Baipan-bhari-g"
  }   ,{
    "name":"Chandra",
    "imgSrc": "songs/Marathi songs/music.png",
    "downloadLink":"songs/Marathi songs/Chandra.mp3",
  "pagename":"Chandra"
  }   ,{
    "name":"Devmanus avtarla",
    "imgSrc": "songs/Marathi songs/music.png",
    "downloadLink":"songs/Marathi songs/Devmanus avtarla.mp3",
  "pagename":"Devmanus-avtarla"
  } ,{
    "name":"Gau nko Kisna",
    "imgSrc": "songs/Marathi songs/music.png",
    "downloadLink":"songs/Marathi songs/Gau nko Kisna.mp3",
  "pagename":"Gau-nko-kisna"
  }   ,{
    "name":"Gulabi sadi aani lali lal",
    "imgSrc": "songs/Marathi songs/music.png",
    "downloadLink":"songs/Marathi songs/Gulabi sadi aani lali lal.mp3",
  "pagename":"Gulabi-sadi"
  }   ,{
    "name":"Jay bhavani jay shivaji",
    "imgSrc": "songs/Marathi songs/music.png",
    "downloadLink":"songs/Marathi songs/Jay bhavani jay shivaji.mp3",
  "pagename":"Jay-bhavani-jay-shivaji"
  }   ,{
    "name":"Jutha pyar hai tera",
    "imgSrc": "songs/Marathi songs/music.png",
    "downloadLink":"songs/Marathi songs/Jutha pyar hai tera.mp3",
  "pagename":"Jutha-pyar-hai-tera"
  }   ,{
    "name":"Kakan",
    "imgSrc": "songs/Marathi songs/music.png",
    "downloadLink":"songs/Marathi songs/Kakan.mp3",
  "pagename":"Kakan"
  }   ,{
    "name":"Kheltuya kel asa maitra",
    "imgSrc": "songs/Marathi songs/music.png",
    "downloadLink":"songs/Marathi songs/Kheltuya kel asa maitra.mp3",
  "pagename":"Kheltuya-khel-asa-maitr"
  }   ,{
    "name":"Kitida nvyane tula aathvave",
    "imgSrc": "songs/Marathi songs/music.png",
    "downloadLink":"songs/Marathi songs/Kitida nvyane tula aathvave.mp3",
  "pagename":"Kitida-nvyane-tula"
  }   ,{
    "name":"Makhmali",
    "imgSrc": "songs/Marathi songs/music.png",
    "downloadLink":"songs/Marathi songs/Makhmali.mp3",
  "pagename":"Makhmali"
  }   ,{
    "name":"Man dhaga dhaga",
    "imgSrc": "songs/Marathi songs/music.png",
    "downloadLink":"songs/Marathi songs/Man dhaga dhaga.mp3",
  "pagename":"Man-dhaga-dhaga"
  }   ,{
    "name":"Maz first love",
    "imgSrc": "songs/Marathi songs/music.png",
    "downloadLink":"songs/Marathi songs/Maz first love .mp3",
  "pagename":"Maz-first-love"
  }   ,{
    "name":"Marathmoli thodi si sadhi bholi",
    "imgSrc": "songs/Marathi songs/music.png",
    "downloadLink":"songs/Marathi songs/Marath moli thodi si sadhi bholi.mp3",
  "pagename":"Marath-moli-thodi-si"
  }   ,{
    "name":"Maza boyfriend pkka selfish hay",
    "imgSrc": "songs/Marathi songs/music.png",
    "downloadLink":"songs/Marathi songs/Maza boyfriend pkka selfish hay.mp3",
  "pagename":"Maza-boyfriend-pakka"
  } ,{
    "name":"Mazi bayko",
    "imgSrc": "songs/Marathi songs/music.png",
    "downloadLink":"songs/Marathi songs/Mazi bayko .mp3",
  "pagename":"Mazi-bayko"
  }   ,{
    "name":"Mazi navri hoshil ka",
    "imgSrc": "songs/Marathi songs/music.png",
    "downloadLink":"songs/Marathi songs/Mazi navri hoshil kay.mp3",
  "pagename":"Mazi-navri-hoshil"
  }   ,{
    "name":"Mi singale",
    "imgSrc": "songs/Marathi songs/music.png",
    "downloadLink":"songs/Marathi songs/Mi singale.mp3",
  "pagename":"Mi-singale"
  }   ,{
    "name":"Na sangtach aaj he kale mala",
    "imgSrc": "songs/Marathi songs/music.png",
    "downloadLink":"songs/Marathi songs/Na sangtach aaj he kle mla.mp3",
  "pagename":"Na-sangtach-aaj"
  }   ,{
    "name":"Navra pahije gora gora",
    "imgSrc": "songs/Marathi songs/music.png",
    "downloadLink":"songs/Marathi songs/Navra pahije gora gora.mp3",
  "pagename":"Navra-pahije-gora"
  }   ,{
    "name":"Navri aali",
    "imgSrc": "songs/Marathi songs/music.png",
    "downloadLink":"songs/Marathi songs/Navri aali.mp3",
  "pagename":"Navri-aali"
  }   ,{
    "name":"Paul thkal nahi",
    "imgSrc": "songs/Marathi songs/music.png",
    "downloadLink":"songs/Marathi songs/Paul thkal nahi.mp3",
  "pagename":"Paul-thakal-nahi"
  }   ,{
    "name":"Payi Phufata rutla kata",
    "imgSrc": "songs/Marathi songs/music.png",
    "downloadLink":"songs/Marathi songs/Payi Phufat rutla kata.mp3",
  "pagename":"Payi-phufata-rutl-kata"
  }   ,{
    "name":"Pori tuze nadan 2",
    "imgSrc": "songs/Marathi songs/music.png",
    "downloadLink":"songs/Marathi songs/Pori tuze nadan 2.mp3",
  "pagename":"Pori-tuze-nadan-2"
  }   ,{
    "name":"Raghu Pinjryat aala",
    "imgSrc": "songs/Marathi songs/music.png",
    "downloadLink":"songs/Marathi songs/Raghu Pinjryat aala.mp3",
  "pagename":"Raghu-Pinjryat-aala"
  }   ,{
    "name":"Rang langla",
    "imgSrc": "songs/Marathi songs/music.png",
    "downloadLink":"songs/Marathi songs/Rang langla.mp3",
  "pagename":"Rang-langla"
  }   ,{
    "name":"Hridayi Vasant Phulatana",
    "imgSrc": "songs/Marathi songs/music.png",
    "downloadLink":"songs/Marathi songs/rdyi vasant phultana.mp3",
  "pagename":"rdyi-vasant-phultana"
  }   ,{
    "name":"Sairat zal ji",
    "imgSrc": "songs/Marathi songs/music.png",
    "downloadLink":"songs/Marathi songs/Sairat zal ji.mp3",
  "pagename":"Sairat-zal-ji"
  }   ,{
    "name":"Sukh kalle",
    "imgSrc": "songs/Marathi songs/music.png",
    "downloadLink":"songs/Marathi songs/Sukh kalle .mp3",
  "pagename":"Sukh-kalle"
  }   ,{
    "name":"Sunya Sunya mnamdhye",
    "imgSrc": "songs/Marathi songs/music.png",
    "downloadLink":"songs/Marathi songs/Sunya Sunya mnamdhye.mp3",
  "pagename":"Sunya-sunya"
  }   ,{
    "name":"Svarg ha nva",
    "imgSrc": "songs/Marathi songs/music.png",
    "downloadLink":"songs/Marathi songs/Svarg ha nva.mp3",
  "pagename":"Svarg-ha-nva"
  }   ,{
    "name":"Tuza lalduupta",
    "imgSrc": "songs/Marathi songs/music.png",
    "downloadLink":"songs/Marathi songs/Tuza lalduupta .mp3",
    "pagename":"Tuza-lalduupta"
  }   ,{
    "name":"Tuzya Priticha ha vinchu",
    "imgSrc": "songs/Marathi songs/music.png",
    "downloadLink":"songs/Marathi songs/Tuzya Priticha ha vinchu.mp3",
  "pagename":"Tuzya-Priticha-ha-vinchu"
  }   ,{
    "name":"Udhal Udhal ho",
    "imgSrc": "songs/Marathi songs/music.png",
    "downloadLink":"songs/Marathi songs/Udhal Udhal ho.mp3",
  "pagename":"Udhal-Udhal-ho"
  }   ,{
    "name":"Umagaya baap ra",
    "imgSrc": "songs/Marathi songs/music.png",
    "downloadLink":"songs/Marathi songs/Umagaya baap ra.mp3",
  "pagename":"Umagaya-baap-ra"
  }   ,{
    "name":"Wajle ki bara",
    "imgSrc": "songs/Marathi songs/music.png",
    "downloadLink":"songs/Marathi songs/Wajle ki bara.mp3",
  "pagename":"Wajle-ki-bara"
  }  ,{
    "name":"Yad lagl g yad lagl g",
    "imgSrc": "songs/Marathi songs/music.png",
    "downloadLink":"songs/Marathi songs/Yad lagl g yad lagl g.mp3",
  "pagename":"Yad-lagl-g"
  }  ,{
    "name":"Zingat",
    "imgSrc": "songs/Marathi songs/music.png",
    "downloadLink":"songs/Marathi songs/zingat.mp3",
  "pagename":"Zingat"
  },
   {
      "name":"Aale Marathe",
      "imgSrc": "songs/Shivaji Maharaj songs/img/Aale Marathe.jpg",
      "downloadLink":"songs/Shivaji Maharaj songs/Aale Marathe.mp3",
    "pagename":"Aale-Marathe"
    },   {
      "name":"Chakar shivbach honar",
      "imgSrc": "songs/Shivaji Maharaj songs/img/chakar shivbach honar.jpg",
      "downloadLink":"songs/Shivaji Maharaj songs/Chakar shivbach honar.mp3",
    "pagename":"Chakar-shivabach-honar"
    },   {
      "name":"Mazya raja r",
      "imgSrc": "songs/Shivaji Maharaj songs/img/mazya raja r.jpg",
      "downloadLink":"songs/Shivaji Maharaj songs/Mazya raja r.mp3",
    "pagename":"Mazya-raja-r"
    },   {
      "name":"Raja Aala",
      "imgSrc": "songs/Shivaji Maharaj songs/img/raj aal.jpg",
      "downloadLink":"songs/Shivaji Maharaj songs/Raja Aala.mp3",
    "pagename":"Raja-Aala"
    },   {
      "name":"Sar rrr holi ka jale - may bhavani",
      "imgSrc": "songs/Shivaji Maharaj songs/img/sar holi ka jale.jpg",
      "downloadLink":"songs/Shivaji Maharaj songs/Sar rrr holi ka jale - may bhavani.mp3",
    "pagename":"Sar-rrr-holi-ka-jale"
    },   {
      "name":"Savari bhavani chauk madhi g",
      "imgSrc": "songs/Shivaji Maharaj songs/img/svari bhavani chauka mdhi.jpg",
      "downloadLink":"songs/Shivaji Maharaj songs/Savari bhavani chauk madhi g.mp3",
    "pagename":"Savari-bhvani-chauka-madhi"
    },   {
      "name":"Shivba Raja",
      "imgSrc": "songs/Shivaji Maharaj songs/img/shivba raja.jpg",
      "downloadLink":"songs/Shivaji Maharaj songs/Shivba Raja .mp3",
    "pagename":"Shivba-raja"
    },   {
      "name":"Shoorveer",
      "imgSrc": "songs/Shivaji Maharaj songs/img/shoorveer.jpeg",
      "downloadLink":"songs/Shivaji Maharaj songs/Shoorveer.mp3",
    "pagename":"Shoorveer"
    },
    {
      "name":"Yugat Mandli",
      "imgSrc": "songs/Shivaji Maharaj songs/img/yugat mandli.jpg",
      "downloadLink":"songs/Shivaji Maharaj songs/Yugat Mandli.mp3",
    "pagename":"Yugat-mandi"
    },
    {
      "name":"Zulva Palna Palna bal shivaji cha",
      "imgSrc": "songs/Shivaji Maharaj songs/img/zulva palna.jpg",
      "downloadLink":"songs/Shivaji Maharaj songs/Zulva Palna Palna bal shivaji cha.mp3",
    "pagename":"Zulva-Palna-bal"
    },{
      "name": "Natrang Ubha",
      "imgSrc": "songs/Gods songs/img/natrangUbha.jpg",
    "downloadLink": "songs/Gods songs/natrang ubha.mp3",
    "pagename":"Natrang-ubha"
    }
    ,{
      "name":"Lallati Bhandar",
      "downloadLink":"songs/Gods songs/Lallati bhandar.mp3",
      "imgSrc": "songs/Gods songs/img/Lallati bhandar.jpg",
    "pagename":"Lallati-Bhandar"
    }
    ,{
      "name":"Bhetla vittal maza",
      "downloadLink":"songs/Gods songs/Bhetla vittal maza.mp3",
     "imgSrc": "songs/Gods songs/img/bhetla vittal maza.jpg",
    "pagename":"Bhetla-vittal-maza"
    }  
    ,{
      "name":"Dev martanda dev malhari",
      "imgSrc": "songs/Gods songs/img/dev martanda dev malhari.jpg",
      "downloadLink":"songs/Gods songs/Dev martanda dev malhari.mp3",
    "pagename":"Dev-martanda"
    }
    ,{
      "name":"Deva kaljachi hak ek ekda tari",
    "imgSrc": "songs/Gods songs/img/deva tuzya gabharyala.jpg",
      "downloadLink":"songs/Gods songs/Deva kaljachi hak aik ek datari.mp3",
    "pagename":"Deva-tuzya-gabharyala"
    }
    ,{
      "name":"Deva shri ganesha",
    "imgSrc": "songs/Gods songs/img/deva shri gnesha.jpg",
      "downloadLink":"songs/Gods songs/Deva shri ganesha.mp3",
    "pagename":"Deva-shri-ganesha"

    }
    ,{
      "name":"Devak kalji re mazya",
    "imgSrc": "songs/Gods songs/img/devak kalji re.jpg",
      "downloadLink":"songs/Gods songs/Devak kalji re mazy.mp3",
    "pagename":"Devak-kalji-re"

    }
    ,{
      "name":"Shree Ganeshay Dheemahi",
      "imgSrc": "songs/Gods songs/img/gannay kay.jpeg",
      "downloadLink":"songs/Gods songs/gannaykay dheemahi.mp3",
    "pagename":"gannaykay"

    }
    ,{
      "name":"nirakar guru guru re nirgun",
    "imgSrc": "songs/Gods songs/img/gurucharitra.webp",
      "downloadLink":"songs/Gods songs/Gurucharitra.mp3",
    "pagename":"Gurucharitra"
    }
    ,{
      "name":"Hechi yel deva naka",
   "imgSrc": "songs/Gods songs/img/hechi yel deva.jpg",
      "downloadLink":"songs/Gods songs/Hechi yel deva naka.mp3",
    "pagename":"Hechi-vel-deva"
    }
    ,{
      "name":"Khel mandla",
     "imgSrc": "songs/Gods songs/img/khel mandla.webp",
      "downloadLink":"songs/Gods songs/Khel mandla.mp3",
    "pagename":"Khel-mandla"
    }
    ,{
      "name":"Malhar wari",
      "imgSrc": "songs/Gods songs/img/malhar wari.jpg",
      "downloadLink":"songs/Gods songs/Malhar wari.mp3",
    "pagename":"Malhar-wari"
    }
    ,{
      "name":"Mauli Mauli",
     "imgSrc": "songs/Gods songs/img/mauli mauli.jpg",
      "downloadLink":"songs/Gods songs/Mauli Mauli.mp3",
    "pagename":"Mauli-Mauli"
    }
    ,{
      "name":"Maze mahir pandhri",
      "imgSrc": "songs/Gods songs/img/maze maher pandhru.jpg",
      "downloadLink":"songs/Gods songs/Maze maher pandhri.mp3",
    "pagename":"Maze-mahir-pandhri"
    }
    ,{
      "name":"Mazi Pandhri chi maay",
      "imgSrc": "songs/Gods songs/img/mazi pandhrichi may.jpg",
      "downloadLink":"songs/Gods songs/Mazi pandhrichi may.mp3",
    "pagename":"Mazi-pandhrichi-may"
    }
    ,{
      "name":"Nam tuze gheta deva",
      "imgSrc": "songs/Gods songs/img/nam tuze gheta deva.jpg",
      "downloadLink":"songs/Gods songs/Nam tuze gheta deva.mp3",
    "pagename":"Nam-tuze-gheta-deva"
    }
    ,{
      "name":"Pandurang pandurang Bolto Mrudang",
     "imgSrc": "songs/Gods songs/img/pandurang pandurng bolto mrudang.jpg",
      "downloadLink":"songs/Gods songs/Pandurang Pandurang Bolto Mrudang.mp3",
    "pagename":"pandurang-Pandurang"
    }
    ,{
      "name":"Rakhumai Rakhumai",
    "imgSrc": "songs/Gods songs/img/rukhmai ukhmai.jpeg",
      "downloadLink":"songs/Gods songs/Rakhumai Rakhumai.mp3",
    "pagename":"Rukhumai-Rukhumai"
    }
    ,{
      "name":"Tulshi mal hi shvasanchi",
     "imgSrc": "songs/Gods songs/img/tulshi mal hi shvsachi.jpg",
      "downloadLink":"songs/Gods songs/Tulshi mal hi shvasanchi.mp3",
    "pagename":"Tulshi-mal-shvasanchi"
    },
    {
      "name":"gondl mandla bhavani gondhla ye",
     "imgSrc": "songs/Gods songs/img/gondhal mandl.jpg",
      "downloadLink":"songs/Gods songs/udh udh udh gondl mandla bhavani gondhla la ye.mp3",
    "pagename":"gondhal-mandala"
    },
    {
      "name":"Vat disu dega deva",
     "imgSrc": "songs/Gods songs/img/vat disu.jpg",
      "downloadLink":"songs/Gods songs/Vat disu dega deva.mp3",
    "pagename":"vat-disu-dega-deva"
    },
    {
      "name":"Vithu mauli tu mauli jagachi",
      "imgSrc": "songs/Gods songs/img/vithu mauli tu mauli jgachi.jpeg",
      "downloadLink":"songs/Gods songs/Vithumauli tu mauli jagachi.mp3",
    "pagename":"Vithumauli-tu-mauli-jagachi"
    },
    {
      "name":"ya re ya sare ya",
      "imgSrc": "songs/Gods songs/img/rukhmai ukhmai.jpeg",
      "downloadLink":"songs/Gods songs/ya re ya sare ya.mp3",
    "pagename":"ya-re-ya-sare-ya"
    }
     
  ]
  